{"title":"에스콰이어 코리아 ─ 카&테크","url":"https://www.esquirekorea.co.kr/carandtech","favicon":"https://www.esquirekorea.co.kr/favicon.ico","elements":[{"title":"미니쿠퍼보다 작은 픽업 트럭 등장","contents":"2026년부터 본격 생산 시작.","link":"https://www.esquirekorea.co.kr/article/78456","retrieved":1687684797910,"image":"https://image.jtbcplus.kr/data/contents/jam_photo/202306/19/b66fda13-8f31-48be-b03d-b4085a5ceb36.jpg"},{"title":"로봇이 배달하는 시대가 온다","contents":"저렴한 배달비와 함께.","link":"https://www.esquirekorea.co.kr/article/78441","retrieved":1687425482262,"image":"https://image.jtbcplus.kr/data/contents/jam_photo/202306/18/d29b448b-ae30-4c60-ab99-6fe7e3110e17.jpg"},{"title":"비틀즈, AI로 완성된 마지막 곡 발매 예정","contents":"AI 기술을 통해 '존 레논'의 목소리를 담아냈다.","link":"https://www.esquirekorea.co.kr/article/78364","retrieved":1687425482264,"image":"https://image.jtbcplus.kr/data/contents/jam_photo/202306/14/e0f548a6-3406-41ff-a805-2cafc8ea0475.jpg"},{"title":"계단 오르는 로봇청소기의 등장","contents":"주변 환경을 감지하는 건 물론, 음성인식도 가능하다.","link":"https://www.esquirekorea.co.kr/article/78341","retrieved":1687252692930,"image":"https://image.jtbcplus.kr/data/contents/jam_photo/202306/13/3d773f94-5df3-4308-b990-c6b5573d3d1c.jpg"},{"title":"도로위를 질주하는 환상적인 컨버터블 7대","contents":"묵은 체증이 싹 가실 만큼 상쾌한 드라이빙을 선사하는 최신 오픈 톱 모델 7대의 면면.","link":"https://www.esquirekorea.co.kr/article/78055","retrieved":1687252692932,"image":"https://image.jtbcplus.kr/data/contents/jam_photo/202306/13/dd6d3cf5-65f7-410c-a29e-38357df7ef5a.jpg"},{"title":"폭스바겐 ID.4의 주행거리가 늘어난 이유는?","contents":"","link":"https://www.esquirekorea.co.kr/article/78290","retrieved":1687166399344,"image":"https://image.jtbcplus.kr/data/contents/jam_photo/202306/12/76c05270-5a7f-4152-8bb5-f9b9a152c999.jpg"},{"title":"땀을 흘리는 휴머노이드 로봇의 등장","contents":"기후 변화에 대비하기 위하여.","link":"https://www.esquirekorea.co.kr/article/78287","retrieved":1687079871370,"image":"https://image.jtbcplus.kr/data/contents/jam_photo/202306/11/53d0d66d-dba5-4e89-8c2f-82730d40373f.jpg"},{"title":"캐딜락의 첫 전기차 리릭의 등장","contents":"","link":"https://www.esquirekorea.co.kr/article/78285","retrieved":1686734294432,"image":"https://image.jtbcplus.kr/data/contents/jam_photo/202306/11/995df8c0-f37a-4007-a356-5bd2b8c5ea64.jpg"}]}