{"title":"에스콰이어 코리아 ─ 푸드","url":"https://www.esquirekorea.co.kr/food","favicon":"https://www.esquirekorea.co.kr/favicon.ico","elements":[{"title":"시원한 동굴 속에서 즐기는 이색 맛집 4","contents":"동굴 속 신비로운 분위기는 물론 시원함까지 더해져 여름 데이트 맛집으로 추천한다.","link":"https://www.esquirekorea.co.kr/article/78545","retrieved":1687512131575},{"title":"먹고 보고 즐긴 베트남 호이안 3박 4일 VLOG","contents":"호이안 어디까지 가봤니?","link":"https://www.esquirekorea.co.kr/article/78544","retrieved":1687512131576},{"title":"가게에서 직접 숙성하는 오향족발 맛집 5","contents":"성시경이 극찬한 족발과 중화요리를 같이 내주는 맛집?","link":"https://www.esquirekorea.co.kr/article/78485","retrieved":1687425491888},{"title":"여름 별미 백김치 국수 맛집 4","contents":"직접 담근 백김치와 열무를 듬뿍 넣어주는 백김치 국수 맛집?","link":"https://www.esquirekorea.co.kr/article/78437","retrieved":1687339137952},{"title":"한우를 튀겨주는 맛집 4","contents":"한우 튀김과 함께 육사시미, 한우 물회까지 맛볼 수 있는 곳?","link":"https://www.esquirekorea.co.kr/article/78422","retrieved":1687339137955},{"title":"뭉텅이로 썰어주는 깍둑 고기 맛집 4","contents":"육즙 팡! 비주얼도 팡!","link":"https://www.esquirekorea.co.kr/article/78419","retrieved":1687339137957},{"title":"서울 동치미 국수 맛집 4","contents":"직화불고기와 함께 즐기는 메밀 동치미국수의 맛?","link":"https://www.esquirekorea.co.kr/article/78415","retrieved":1687339137959},{"title":"‘미쉐린 가이드 서울 2023’에 선정된 콩국수 맛집 5","contents":"합리적인 가격에 훌륭한 음식을 맛볼 수 있는 콩국수 ‘찐’ 맛집을 소개한다.","link":"https://www.esquirekorea.co.kr/article/78408","retrieved":1687274376772}]}