{"title":"에스콰이어 코리아 ─ 푸드","url":"https://www.esquirekorea.co.kr/food","favicon":"https://www.esquirekorea.co.kr/favicon_esq.ico?v=20190812","elements":[{"title":"요즘 뜨는 용산공원 근처 맛집 5","contents":"공원만 들렀다 가기엔 아쉽다면 주목하자.","link":"https://www.esquirekorea.co.kr/article/61162","retrieved":1637047202553,"image":"https://image.jtbcplus.kr/data/contents/jam_photo/202111/13/e8bed3b5-6ae7-4362-98cc-8a6c2e61badc.jpg"},{"title":"추운 겨울도 문제없는 야외 온천 리조트 4","contents":"가족은 물론 연인과 가기도 좋은 청송, 제천, 울진, 양양에 위치한 야외 온천을 즐길 수 있...","link":"https://www.esquirekorea.co.kr/article/61150","retrieved":1637032874338,"image":"https://image.jtbcplus.kr/data/contents/jam_photo/202111/15/8e548920-2978-45c1-9d43-80d45942774c.jpg"},{"title":"변신의 귀재 윤계상 맛집 5","contents":"작품마다 다양한 변신을 거듭해 화제를 불러 모으는 윤계상. 그는 어떤 식당을 다녀갔을까?","link":"https://www.esquirekorea.co.kr/article/61140","retrieved":1636960808284,"image":"https://image.jtbcplus.kr/data/contents/jam_photo/202111/12/6ce5eaa2-5e49-4a02-b3b7-e50e3fe2b4db.jpg"},{"title":"믿고 보는 식객 끝판왕 허영만의 단골 맛집 4","contents":"방송 프로그램 ‘식객 허영만의 백반기행’에 나오는 식당이 아니라 허영만 화백이 직접 다니는 ...","link":"https://www.esquirekorea.co.kr/article/61131","retrieved":1636860070660,"image":"https://image.jtbcplus.kr/data/contents/jam_photo/202111/15/40aad290-d063-4995-8434-a6927fbe3224.jpg"},{"title":"동해에서 부산까지 호텔 컨셉 카페 5","contents":"색다른 영감을 불러줄 전국 각지의 호텔 컨셉 카페를 찾아가봤다.","link":"https://www.esquirekorea.co.kr/article/61108","retrieved":1636795193082,"image":"https://image.jtbcplus.kr/data/contents/jam_photo/202111/11/40219fdc-b3b5-4d28-b622-8de7d321056c.jpg"},{"title":"미국의 패스트푸드 체인 아비스 ‘감자튀김 맛 보드카’ 출시","contents":"한정판으로 출시된다.","link":"https://www.esquirekorea.co.kr/article/61100","retrieved":1636791784644,"image":"https://image.jtbcplus.kr/data/contents/jam_photo/202111/11/4fd17fd0-cf14-451d-9558-5961267b9515.jpg"},{"title":"‘땡땡거리 맛집’ 서울 기찻길 옆 낭만 식당들 5","contents":"아직 서울에도 ‘땡땡’ 소리를 들을 수 있는 기찻길 건널목들이 있다. 그 바로 옆에서 신호음...","link":"https://www.esquirekorea.co.kr/article/61086","retrieved":1636734646839,"image":"https://image.jtbcplus.kr/data/contents/jam_photo/202111/11/2f2b6d97-8972-4f39-ad72-bf18b61e6106.jpg"},{"title":"더 벤티 x 오뚜기 '멜팅참깨라떼' 출시","contents":"12월 한 달 동안 만나볼 수 있다.","link":"https://www.esquirekorea.co.kr/article/61083","retrieved":1636708884575,"image":"https://image.jtbcplus.kr/data/contents/jam_photo/202111/10/ec256483-841f-45a4-99db-a5b8144987f0.jpg"}]}