{"title":"에스콰이어 코리아 ─ 푸드","url":"https://www.esquirekorea.co.kr/food","favicon":"https://www.esquirekorea.co.kr/favicon.ico","elements":[{"title":"레트로 감성 그대로! 호프 치킨 맛집","contents":"간판부터 남다르다.","link":"https://www.esquirekorea.co.kr/article/81871","retrieved":1699435093427},{"title":"전국 각지에서 찾은 제철 맞은 석화 맛집 4","contents":"석화찜, 구이, 순두부, 회까지 메뉴도 다양하다.","link":"https://www.esquirekorea.co.kr/article/81857","retrieved":1699024726028},{"title":"이발관의 변신은 어디까지? 이발관 술집 3","contents":"겉과 속이 철저히 다르다.","link":"https://www.esquirekorea.co.kr/article/81856","retrieved":1699024726043},{"title":"K팝 역대 초동 1위! 세븐틴 맛집","contents":"세븐틴이 회식을 즐긴 장소?","link":"https://www.esquirekorea.co.kr/article/81826","retrieved":1699024726045},{"title":"11월 1일은 한우의 날! 이색 한우 맛집 4","contents":"한우 케이크, 회전 레일 한우, 불쇼 한우, 한우 갈비 파이까지.","link":"https://www.esquirekorea.co.kr/article/81817","retrieved":1699003124495},{"title":"균류의 대표주자인 버섯이 최고의 식재료로 떠오른 이유","contents":"‘부패’나 ‘독’ 등의 단어를 떠올리게 하는 균류의 대표 주자 버섯은 이제 누구나 먹고 싶어...","link":"https://www.esquirekorea.co.kr/article/81639","retrieved":1698938303390},{"title":"서울에서 맛보는 독도새우 맛집 4","contents":"새우계의 에르메스.","link":"https://www.esquirekorea.co.kr/article/81728","retrieved":1698916635433},{"title":"일러스트레이터 키크니의 <일러바치기> 전시회와 신사 데이트 풀코스 5","contents":"전시회부터 맛집, 카페, 레코드 바까지 분위기 좋은 곳으로 엄선했다.","link":"https://www.esquirekorea.co.kr/article/81691","retrieved":1698916635434}]}