{"title":"에스콰이어 코리아 ─ 라이프","url":"https://www.esquirekorea.co.kr/life","favicon":"https://www.esquirekorea.co.kr/favicon.ico","elements":[{"title":"손흥민 '토트넘 홋스퍼' 주장 발탁","contents":"보고 싶었던 캡틴 SON.","link":"https://www.esquirekorea.co.kr/article/79873","retrieved":1692350238385},{"title":"크리스토퍼 놀란 영화 실제 인물 ‘오펜하이머’ TMI 12.","contents":"대학 시절 교수님을 끌어 내리고 본인이 수업했다고?","link":"https://www.esquirekorea.co.kr/article/79867","retrieved":1692350238388},{"title":"한끼 1만원 이하, 만원으로 즐기는 동묘앞 가성비 노포 4","contents":"함께 즐겨요, 만원의 행복.","link":"https://www.esquirekorea.co.kr/article/79852","retrieved":1692285486306},{"title":"[돈두댓 서베이] 내가 경험한 이색 섹스 장소","contents":"먼저 주위를 잘 둘러보세요","link":"https://www.esquirekorea.co.kr/article/79848","retrieved":1692263862322},{"title":"'콘크리트 유토피아'로 돌아온 이병헌, 이민정 부부 맛집 4","contents":"톱스타 부부가 다녀간 전국 맛집을 파헤쳐 보자.","link":"https://www.esquirekorea.co.kr/article/79843","retrieved":1692177451088},{"title":"주말에만 운영하는 귀한 카페 4","contents":"오픈런 필수! 크루아상 맛집부터 동화 속 감성 카페까지","link":"https://www.esquirekorea.co.kr/article/79837","retrieved":1692026250186},{"title":"JTBC 드라마 '힙하게' 내일 첫 방송","contents":"한지민과 이민기가 출연한다.","link":"https://www.esquirekorea.co.kr/article/79831","retrieved":1692004662159},{"title":"고규필 짜파게티 광고 비하인드 썰?","contents":"","link":"https://www.esquirekorea.co.kr/article/79828","retrieved":1691831786718}]}