{"title":"에스콰이어 코리아 ─ 라이프","url":"https://www.esquirekorea.co.kr/life","favicon":"https://www.esquirekorea.co.kr/favicon.ico","elements":[{"title":"혼술하기 좋은 모던 위스키 바 4","contents":"고요한 분위기에서 즐기는 한잔의 위스키.","link":"https://www.esquirekorea.co.kr/article/80170","retrieved":1693235940709},{"title":"공덕 족발 골목 찐 맛집 4","contents":"50년 넘게 운영한 노포 족발집부터 서비스로 머릿고기, 순대, 떡볶이가 나오는 곳까지.","link":"https://www.esquirekorea.co.kr/article/80159","retrieved":1693235940710},{"title":"서울 양꼬치 무한리필 맛집 4","contents":"원하는 대로 양껏 골라 먹는 재미! 양꼬치 무한리필 집을 소개한다.","link":"https://www.esquirekorea.co.kr/article/80147","retrieved":1693214318856},{"title":"서울 금호동 금남시장 맛집 4","contents":"트와이스 지효의 단골 보쌈집이 있는 그 곳, 정겨운 금남시장 속 맛집을 모았다.","link":"https://www.esquirekorea.co.kr/article/80117","retrieved":1693106271452},{"title":"전·현직 대사관 셰프가 운영하는 서울 맛집 4","contents":"베테랑 셰프들의 진짜 노하우가 담겨 있다.","link":"https://www.esquirekorea.co.kr/article/80093","retrieved":1693041373799},{"title":"신혜선 주연, 영화 '타겟' 개봉 D-7","contents":"신혜선의 첫 스릴러 도전.","link":"https://www.esquirekorea.co.kr/article/80080","retrieved":1693019866277},{"title":"스트레이키즈, 2023 MTV 비디오 뮤직 어워즈 출연","contents":"시상식은 9월 12일 예정.","link":"https://www.esquirekorea.co.kr/article/80052","retrieved":1693019866279},{"title":"넷플릭스 ‘마스크걸’ 주오남을 삼킨 안재홍 TMI 12.","contents":"‘마스크걸’ 일본어 연기는 모두 애드리브?","link":"https://www.esquirekorea.co.kr/article/79988","retrieved":1692955054073}]}