{"title":"에스콰이어 코리아 ─ 라이프","url":"https://www.esquirekorea.co.kr/life","favicon":"https://www.esquirekorea.co.kr/favicon.ico","elements":[{"title":"블랙핑크, 'Kill This Love' 뮤직비디오 19억 뷰 돌파","contents":"K 팝 아티스트 최초로 19억 뷰 이상 뮤직비디오 두 편을 보유하게 됐다.","link":"https://www.esquirekorea.co.kr/article/82675","retrieved":1701876001958},{"title":"올해 책을 낸 소설가 3명이 들려준 '이 책의 주요 대목을 썼던 장소들'","contents":"어떤 이야기는 꼭 그것이 태어날 법한 장소에서 만들어지는가 하면, 어떤 이야기는 엉뚱한 곳에...","link":"https://www.esquirekorea.co.kr/article/82360","retrieved":1701854352253},{"title":"Part 2. 세계각지에서 보내온 추천 \"한국어로 번역되어야 할 올해의 책\"","contents":"해외에 거주하는 책 좀 읽는 사람들에게 물었다. 2023년에 당신의 거주국에서 출간된 책 중 한...","link":"https://www.esquirekorea.co.kr/article/82329","retrieved":1701854352256},{"title":"Part 1. 세계각지에서 보내온 추천 \"한국어로 번역되어야 할 올해의 책\"","contents":"해외에 거주하는 책 좀 읽는 사람들에게 물었다. 2023년에 당신의 거주국에서 출간된 책 중 한...","link":"https://www.esquirekorea.co.kr/article/82323","retrieved":1701789642357},{"title":"‘서울의 봄’으로 돌아온 황정민이 다녀간 맛집 4","contents":"부인과 데이트 시절부터 자주 가던 곳은 어디?","link":"https://www.esquirekorea.co.kr/article/82651","retrieved":1701703187408},{"title":"2024 블루리본 서베이 선정 신규 카페 4","contents":"덴마크에서 직접 로스팅한 원두를 맛볼 수 있는 곳은?","link":"https://www.esquirekorea.co.kr/article/82648","retrieved":1701660015554},{"title":"연말 파티를 위한 술 마시는 게임 펍 4","contents":"보드게임은 기본! 다트 머신부터 레트로 게임까지.","link":"https://www.esquirekorea.co.kr/article/82647","retrieved":1701573551103},{"title":"룰루레몬이 제안하는, 소중한 사람들을 위한 2023 홀리데이 남녀 기프트 제안","contents":"프리미엄 스포츠웨어 브랜드 룰루레몬에서 홀리데이 시즌에 맞춰 ‘윈터 화이트’ 컬렉션을 선보인...","link":"https://www.esquirekorea.co.kr/article/82639","retrieved":1701444022003}]}