{"title":"에스콰이어 코리아 ─ 나우","url":"https://www.esquirekorea.co.kr/now","favicon":"https://www.esquirekorea.co.kr/favicon.ico","elements":[{"title":"약을 먹지 않고 설사 멈추는 방법 4","contents":"약을 구할 수 없을 때 알아두면 유용하다.","link":"https://www.esquirekorea.co.kr/article/78088","retrieved":1686907111881,"image":"https://image.jtbcplus.kr/data/contents/jam_photo/202306/02/fa04f8f9-ad98-4aec-a78d-d109296452fd.jpg"},{"title":"일론 머스크가 세계 최고 부자 타이틀을 탈환했다","contents":"그렇다면 2위는 누구?","link":"https://www.esquirekorea.co.kr/article/78086","retrieved":1686885669561,"image":"https://image.jtbcplus.kr/data/contents/jam_photo/202306/02/562d96c3-9752-4bee-853b-8b2121787f98.jpg"},{"title":"요즘 핫한 유전자 검사는 어디서 하면 좋을까?","contents":"세계에서 가장 포괄적인 유전자 검사 키트 서클 DNA에 대해서","link":"https://www.esquirekorea.co.kr/article/77983","retrieved":1686388664692,"image":"https://image.jtbcplus.kr/data/contents/jam_photo/202305/31/35771455-d391-43c3-94c4-495757094a06.jpg"},{"title":"세티스파이 X 오클리 협업 아이템 공개","contents":"프랑스의 감성과 미국의 기술력이 만났을 때.","link":"https://www.esquirekorea.co.kr/article/77827","retrieved":1686216004141,"image":"https://image.jtbcplus.kr/data/contents/jam_photo/202305/24/2705f422-cdb0-4130-96ec-4147655b4c8c.jpg"},{"title":"거사를 앞두고 사정량 늘리는 방법 4","contents":"차오르는 느낌이 다르다.","link":"https://www.esquirekorea.co.kr/article/77825","retrieved":1685697495044,"image":"https://image.jtbcplus.kr/data/contents/jam_photo/202305/24/81014e47-a54e-4a15-af53-c913d92705d5.jpg"},{"title":"비욘세와 제이지가 캘리포니아에서 가장 비싼 집을 구입했다","contents":"가격은 얼마?","link":"https://www.esquirekorea.co.kr/article/77823","retrieved":1685697495048,"image":"https://image.jtbcplus.kr/data/contents/jam_photo/202305/24/c0a571a0-75ab-405d-812e-22332cbd21cf.jpg"},{"title":"두바이에 거대한 달 모형 리조트 개발 추진","contents":"총사업비 약 7조 원에 이른다.","link":"https://www.esquirekorea.co.kr/article/77752","retrieved":1685697495049,"image":"https://image.jtbcplus.kr/data/contents/jam_photo/202305/23/f847a8ee-9750-4fd4-a8e7-91bf40d0850e.jpg"},{"title":"에르메스에서 출시한 에어팟 프로 2 케이스","contents":"에어팟 4개 가격과 맞멎는다.","link":"https://www.esquirekorea.co.kr/article/77751","retrieved":1685438342254,"image":"https://image.jtbcplus.kr/data/contents/jam_photo/202305/23/fedf096c-42fe-4e75-8cb2-a922a742159c.jpg"}]}