{"title":"에스콰이어 코리아 ─ 피플","url":"https://www.esquirekorea.co.kr/people","favicon":"https://www.esquirekorea.co.kr/favicon.ico","elements":[{"title":"슈퍼스타는 슈퍼카만 타요, 비욘세 CAR 컬렉션","contents":"보기만 해도 입이 떡 벌어지는 초호화 슈퍼카.","link":"https://www.esquirekorea.co.kr/article/84328","retrieved":1708420733886},{"title":"프라다를 입고 담은 엔하이픈의 청춘 영화","contents":"","link":"https://www.esquirekorea.co.kr/article/84327","retrieved":1708420733890},{"title":"세븐틴 픽 나나투어 이탈리아 맛집 3","contents":"젤라또, 햄버거 그리고 샌드위치까지!","link":"https://www.esquirekorea.co.kr/article/84304","retrieved":1708399149990},{"title":"자동차만 16대? 켄달 제너 CAR 컬렉션","contents":"초호화 럭셔리 슈퍼카부터 클래식한 빈티지 카까지.","link":"https://www.esquirekorea.co.kr/article/84300","retrieved":1708399149991},{"title":"캐나다 청년 로건이 다녀간 전국 맛집 5","contents":"","link":"https://www.esquirekorea.co.kr/article/84290","retrieved":1708334338467},{"title":"2024 셀럽들의 설날 인사","contents":"몬스타엑스부터 투어스까지.","link":"https://www.esquirekorea.co.kr/article/84246","retrieved":1708247863301},{"title":"락 네이션과 베르사체 파트너십 체결","contents":"2024 슈퍼볼에서 첫 공식행사 선보일 예정.","link":"https://www.esquirekorea.co.kr/article/84243","retrieved":1708247863310},{"title":"화폭 같은 몽클레르 그레노블 24 FW 컬렉션","contents":"몽클레르 그레노블 24 FW 런웨이가 스위스 생모리츠에서 열렸다. 글로벌 앰배서더 황민현이 참석...","link":"https://www.esquirekorea.co.kr/article/84207","retrieved":1707988861044}]}