{"title":"에스콰이어 코리아 ─ 피플","url":"https://www.esquirekorea.co.kr/people","favicon":"https://www.esquirekorea.co.kr/favicon.ico","elements":[{"title":"방탄소년단 정국, 캘빈클라인 글로벌 엠버서더 발탁","contents":"정국은 원래도 캘빈클라인의 팬이었다.","link":"https://www.esquirekorea.co.kr/article/76244","retrieved":1680578413254,"image":"https://image.jtbcplus.kr/data/contents/jam_photo/202303/28/6204e36f-0759-4ec2-a65a-1d7d38456649.jpg"},{"title":"세계선수권 대회에서 은메달을 딴 차준환 선수. 아역배우 출신 차준환의 TMI 11.","contents":"차준환이 생각하는 깻잎 논쟁은?","link":"https://www.esquirekorea.co.kr/article/76238","retrieved":1680189833838,"image":"https://image.jtbcplus.kr/data/contents/jam_photo/202303/28/37074234-64e8-4875-95a4-d6cf81f10a5a.jpg"},{"title":"<그것이 알고 싶다>의 간판 PD 배정훈이 '100% 리얼 수사 다큐멘터리' <국가수사본부>로 돌아온 이유","contents":"&lt;그것이 알고 싶다&gt;의 간판 PD 배정훈이  ‘100% 리얼 수사 다큐멘터리’ &lt;국가수사본부&gt;로 돌...","link":"https://www.esquirekorea.co.kr/article/75984","retrieved":1680168173953,"image":"https://image.jtbcplus.kr/data/contents/jam_photo/202303/28/ce5cf631-5e61-4256-9775-641ed01c4d6f.jpg"},{"title":"NCT 도재정 'PERFUME' 티저 공개","contents":"이들의 첫 미니앨범은 4월 17일 발매된다.","link":"https://www.esquirekorea.co.kr/article/76183","retrieved":1680168173955,"image":"https://image.jtbcplus.kr/data/contents/jam_photo/202303/27/317f942d-9578-447f-b5e3-3260385073d4.jpg"},{"title":"마쓰다(마츠다) 부장이 말한다 \"오사카에선 줄 서지 마세요\"","contents":"맛있는 걸 위해 죽음을 불사하는 오사카인, 그러나 부대 앞 할아버지가 ‘쇼팅깡’에 끓여 준 ...","link":"https://www.esquirekorea.co.kr/article/76035","retrieved":1680081767271,"image":"https://image.jtbcplus.kr/data/contents/jam_photo/202303/27/3dff6513-edd2-4684-be2a-15a6392ca753.jpg"},{"title":"파리에 사는 인도인, 서울에 사는 스위스인, 바르셀로나에 사는 리투아니아인이 도시에 대한 유튜브를 만든 이유","contents":"이국 도시에 살며, 전 세계를 향해 그 도시의 삶에 대해 말하고 있는 사람들. 유튜버 여섯 명...","link":"https://www.esquirekorea.co.kr/article/75953","retrieved":1680016956235,"image":"https://image.jtbcplus.kr/data/contents/jam_photo/202303/28/c3aaf20c-d562-415e-a287-e8aefb5b234e.jpg"},{"title":"안희연, 촬영 중 정수리 물린 사건?","contents":"","link":"https://www.esquirekorea.co.kr/article/76127","retrieved":1679995316698,"image":"https://image.jtbcplus.kr/data/contents/jam_photo/202303/24/dda52e78-7787-4cda-9c4b-d903fc73b817.jpg"},{"title":"Part2. 차주영이 말하는 <진짜가 나타났다!> 장세진과 차주영의 싱크로율","contents":"차주영은 자유분방함을 추구하지만 보수적이고, 동시에 어떤 선 안에 자신을 가두고 싶진 않다. ...","link":"https://www.esquirekorea.co.kr/article/75982","retrieved":1679930555345,"image":"https://image.jtbcplus.kr/data/contents/jam_photo/202303/24/2b2692e6-bf15-43f9-8cb6-7c931a5852ab.jpg"}]}