{"title":"에스콰이어 코리아 ─ 스타일","url":"https://www.esquirekorea.co.kr/style","favicon":"https://www.esquirekorea.co.kr/favicon.ico","elements":[{"title":"<사랑이라 말해요> 배우 안희연 화보 공개","contents":"청초하면서도 도발적인 양가적 매력을 발산했다.","link":"https://www.esquirekorea.co.kr/article/76110","retrieved":1680448644685,"image":"https://image.jtbcplus.kr/data/contents/jam_photo/202303/24/683a02da-806c-42bc-b29b-9ef6a8ef9ae8.jpg"},{"title":"PARIS SYNDROME","contents":"셀린느 옴므의 2023년 겨울 컬렉션.","link":"https://www.esquirekorea.co.kr/article/76043","retrieved":1680362271918,"image":"https://image.jtbcplus.kr/data/contents/jam_photo/202303/24/06cb1729-aa8e-47ff-b43b-34f593902918.jpg"},{"title":"올봄 교복은 이것!","contents":"편안한 걸 좋아하는 커플에게 이 옷을 추천한다.","link":"https://www.esquirekorea.co.kr/article/76087","retrieved":1680362271923,"image":"https://image.jtbcplus.kr/data/contents/jam_photo/202303/23/159c4aa8-24d3-4756-8412-7b98759ec644.jpg"},{"title":"지구 끝까지 달려도 편안한 커플 러닝화","contents":"평소에도 신고 다니고 싶을 정도로 편하고 예쁜 커플 러닝화를 소개한다.","link":"https://www.esquirekorea.co.kr/article/76086","retrieved":1680016856601,"image":"https://image.jtbcplus.kr/data/contents/jam_photo/202303/23/7770ca3e-da2d-43bb-8a23-7dd70ff442fb.jpg"},{"title":"데이트 필수품, 이세이미야케","contents":"그녀에게 더 잘 보이고 싶다면 이세이미야케를 뿌리자.","link":"https://www.esquirekorea.co.kr/article/76085","retrieved":1679843878629,"image":"https://image.jtbcplus.kr/data/contents/jam_photo/202303/23/15465416-c671-46d1-b991-49d3e7534659.jpg"},{"title":"디올 맨의 2023 Fall 컬렉션","contents":"이집트 가자지구의 피라미드를 배경으로 펼쳐졌던 디올 맨 2023 Fall 컬렉션. 생경한 아름다움이...","link":"https://www.esquirekorea.co.kr/article/76047","retrieved":1679649534559,"image":"https://image.jtbcplus.kr/data/contents/jam_photo/202303/23/51e42b81-0e96-4ce5-8c41-3dd6cfd46fa8.jpg"},{"title":"크롭의 계절","contents":"여전히 올라가는 중.","link":"https://www.esquirekorea.co.kr/article/76056","retrieved":1679584772590,"image":"https://image.jtbcplus.kr/data/contents/jam_photo/202303/23/458301c6-411d-43ff-a0c2-b3108310c314.jpg"},{"title":"GUIDED BY THE STARS","contents":"피라미드를 배경으로 펼쳐진 디올 맨 2023 가을 컬렉션","link":"https://www.esquirekorea.co.kr/article/76055","retrieved":1679563157299,"image":"https://image.jtbcplus.kr/data/contents/jam_photo/202303/23/5fbe4735-ed41-4f7a-91d8-95df224a3703.jpg"}]}