{"title":"에스콰이어 코리아 ─ 스타일","url":"https://www.esquirekorea.co.kr/style","favicon":"https://www.esquirekorea.co.kr/favicon.ico","elements":[{"title":"한옥으로 떠났다","contents":"슈트를 꺼내 입은 어느 조용한 가을날.","link":"https://www.esquirekorea.co.kr/article/81069","retrieved":1697123932616},{"title":"요즘 자주 꺼내드는 옷을 묻다","contents":"","link":"https://www.esquirekorea.co.kr/article/81038","retrieved":1697123932617},{"title":"여전히 아름다운 구찌의 2024 S/S 컬렉션","contents":"견고하고 강렬한 존재감으로 새로운 시작을 알렸다.","link":"https://www.esquirekorea.co.kr/article/80896","retrieved":1697080700521},{"title":"입장하기 위해 누드모델 사이를 지나야 하는 전시회?","contents":"이것이 바로 행위 예술.","link":"https://www.esquirekorea.co.kr/article/80808","retrieved":1697015919496},{"title":"벨루티와 장기용이 풀어낸 클래식의 현재적 표상","contents":"컨템퍼러리 럭셔리의 본질, 시대와 유행을 초월한 우아함. 장기용과 벨루티 2023 F/W 컬렉션의 ...","link":"https://www.esquirekorea.co.kr/article/80753","retrieved":1696648667267},{"title":"남성성과 여성성을 넘나드는 펜디의 양면성","contents":"테일러링과 드레이핑, 날카로움과 우아함, 남성성과 여성성을 넘나드는 펜디의 양면성.","link":"https://www.esquirekorea.co.kr/article/80737","retrieved":1696389531245},{"title":"경계를 넓힌 MA-1 재킷","contents":"","link":"https://www.esquirekorea.co.kr/article/80646","retrieved":1696086992833},{"title":"셀린느, 뷔와 함께한 도쿄에서의 어느 오후","contents":"다시 만난 BTS 뷔.","link":"https://www.esquirekorea.co.kr/article/80643","retrieved":1695719878988}]}